fashn_human_parser/__init__.py
fashn_human_parser/labels.py
fashn_human_parser/parser.py
fashn_human_parser-0.1.0.dist-info/METADATA
fashn_human_parser-0.1.0.dist-info/WHEEL
fashn_human_parser-0.1.0.dist-info/licenses/LICENSE
fashn_human_parser-0.1.0.dist-info/RECORD
