Metadata-Version: 2.4
Name: fashn-human-parser
Version: 0.1.0
Summary: Human parsing model for fashion and virtual try-on applications
Project-URL: Homepage, https://github.com/fashn-AI/fashn-human-parser
Project-URL: Documentation, https://huggingface.co/fashn-ai/fashn-human-parser
Project-URL: Repository, https://github.com/fashn-AI/fashn-human-parser
Project-URL: Issues, https://github.com/fashn-AI/fashn-human-parser/issues
Author-email: FASHN AI <dan@fashn.ai>
License: See LICENSE
License-File: LICENSE
Keywords: computer-vision,deep-learning,fashion,human-parsing,segmentation,virtual-try-on
Classifier: Development Status :: 4 - Beta
Classifier: Intended Audience :: Developers
Classifier: Intended Audience :: Science/Research
Classifier: Programming Language :: Python :: 3
Classifier: Programming Language :: Python :: 3.8
Classifier: Programming Language :: Python :: 3.9
Classifier: Programming Language :: Python :: 3.10
Classifier: Programming Language :: Python :: 3.11
Classifier: Programming Language :: Python :: 3.12
Classifier: Topic :: Scientific/Engineering :: Artificial Intelligence
Classifier: Topic :: Scientific/Engineering :: Image Processing
Requires-Python: >=3.8
Requires-Dist: numpy>=1.20
Requires-Dist: opencv-python>=4.8
Requires-Dist: pillow>=9.0
Requires-Dist: torch>=2.2
Requires-Dist: transformers>=4.30
Provides-Extra: dev
Requires-Dist: pytest-cov>=4.0; extra == 'dev'
Requires-Dist: pytest>=7.0; extra == 'dev'
